{"title":"马克思主义基本原理概论","uid":"b64390823c66c02c40ea7ccdd7ee2430","slug":"马克思主义基本原理概论","date":"2022-02-05T09:48:42.000Z","updated":"2022-02-05T10:01:03.148Z","comments":true,"path":"api/articles/马克思主义基本原理概论.json","keywords":null,"cover":null,"content":"<h1 id=\"第一章-马克思主义是关于无产阶级和人类解放的科学\"><a href=\"#第一章-马克思主义是关于无产阶级和人类解放的科学\" class=\"headerlink\" title=\"第一章 马克思主义是关于无产阶级和人类解放的科学\"></a>第一章 马克思主义是关于无产阶级和人类解放的科学</h1><h2 id=\"第一节-马克思主义的创立与发展\"><a href=\"#第一节-马克思主义的创立与发展\" class=\"headerlink\" title=\"第一节 马克思主义的创立与发展\"></a>第一节 马克思主义的创立与发展</h2><h3 id=\"一-马克思主义和马克思主义基本原理\"><a href=\"#一-马克思主义和马克思主义基本原理\" class=\"headerlink\" title=\"一 马克思主义和马克思主义基本原理\"></a>一 马克思主义和马克思主义基本原理</h3><blockquote><span class=\"custom-blockquote-svg\"><svg width=\"24\" height=\"24\" viewBox=\"0 0 24 24\" fill=\"\" xmlns=\"http://www.w3.org/2000/svg\" data-reactroot=\"\">\n<path fill=\"\" d=\"M22 12C22 6.5 17.5 2 12 2C6.5 2 2 6.5 2 12C2 17.5 6.5 22 12 22C13.8 22 15.5 21.5 17 20.6L22 22L20.7 17C21.5 15.5 22 13.8 22 12Z\" undefined=\"1\"></path>\n<path fill=\"\" d=\"M15.97 11.5H16.04C17.12 11.5 18 12.38 18 13.47V13.53C18 14.62 17.12 15.5 16.03 15.5H15.96C14.88 15.5 14 14.62 14 13.53V13.46C14 12.38 14.88 11.5 15.97 11.5Z\" undefined=\"1\"></path>\n<path fill=\"\" d=\"M7.97 11.5H8.04C9.12 11.5 10 12.38 10 13.47V13.53C10 14.62 9.12 15.5 8.03 15.5H7.97C6.88 15.5 6 14.62 6 13.53V13.46C6 12.38 6.88 11.5 7.97 11.5Z\" undefined=\"1\"></path>\n<path stroke-linejoin=\"round\" stroke-linecap=\"round\" stroke-miterlimit=\"10\" stroke-width=\"2\" stroke=\"\" d=\"M17 8.5C15.23 8.97 14.07 10.84 14.01 13.27C14 13.33 14 13.4 14 13.47V13.5\"></path>\n<path stroke-linejoin=\"round\" stroke-linecap=\"round\" stroke-miterlimit=\"10\" stroke-width=\"2\" stroke=\"\" d=\"M9 8.5C7.23 8.97 6.07 10.84 6.01 13.27C6 13.33 6 13.4 6 13.47V13.5\"></path>\n<path stroke-linejoin=\"round\" stroke-linecap=\"round\" stroke-miterlimit=\"10\" stroke-width=\"2\" stroke=\"\" d=\"M15.97 11.5H16.04C17.12 11.5 18 12.38 18 13.47V13.53C18 14.62 17.12 15.5 16.03 15.5H15.96C14.88 15.5 14 14.62 14 13.53V13.46C14 12.38 14.88 11.5 15.97 11.5Z\"></path>\n<path stroke-linejoin=\"round\" stroke-linecap=\"round\" stroke-miterlimit=\"10\" stroke-width=\"2\" stroke=\"\" d=\"M7.97 11.5H8.04C9.12 11.5 10 12.38 10 13.47V13.53C10 14.62 9.12 15.5 8.03 15.5H7.97C6.88 15.5 6 14.62 6 13.53V13.46C6 12.38 6.88 11.5 7.97 11.5Z\"></path>\n</svg>\n</span><blockquote>\n<blockquote>\n<p>概括地说，马克思主义是马克思、恩格斯创立的，为他们的后继者不断发展的科学理论体系，马克思主义是关于无产阶级和人类解放的科学。马克思主义哲学、马克思主义政治经济学和科学社会主义，是马克思主义理论体系的三个基本组成部分。<br>马克思主义基本原理是对马克思主义的立场、观点和方法的集中概括。</p></blockquote>\n</blockquote>\n</blockquote>\n<h3 id=\"二-马克思主义的创立\"><a href=\"#二-马克思主义的创立\" class=\"headerlink\" title=\"二 马克思主义的创立\"></a>二 马克思主义的创立</h3><h4 id=\"（一）-马克思主义产生的社会根源、阶级基础和思想渊源\"><a href=\"#（一）-马克思主义产生的社会根源、阶级基础和思想渊源\" class=\"headerlink\" title=\"（一） 马克思主义产生的社会根源、阶级基础和思想渊源\"></a>（一） 马克思主义产生的社会根源、阶级基础和思想渊源</h4><h5 id=\"1-资本主义经济的发展为马克思主义的产生提供了经济、社会、历史条件\"><a href=\"#1-资本主义经济的发展为马克思主义的产生提供了经济、社会、历史条件\" class=\"headerlink\" title=\"1.资本主义经济的发展为马克思主义的产生提供了经济、社会、历史条件\"></a>1.资本主义经济的发展为马克思主义的产生提供了经济、社会、历史条件</h5><h5 id=\"2-无产阶级在反抗资产阶级的斗争中逐步走向自觉，对科学理论的指导提出了强烈的需求（马克思主义产生的阶级基础和实践基础）\"><a href=\"#2-无产阶级在反抗资产阶级的斗争中逐步走向自觉，对科学理论的指导提出了强烈的需求（马克思主义产生的阶级基础和实践基础）\" class=\"headerlink\" title=\"2.无产阶级在反抗资产阶级的斗争中逐步走向自觉，对科学理论的指导提出了强烈的需求（马克思主义产生的阶级基础和实践基础）\"></a>2.无产阶级在反抗资产阶级的斗争中逐步走向自觉，对科学理论的指导提出了强烈的需求（马克思主义产生的阶级基础和实践基础）</h5><h5 id=\"3-马克思、恩格斯的革命实践和对人类文明成果的继承与创新（主观条件）\"><a href=\"#3-马克思、恩格斯的革命实践和对人类文明成果的继承与创新（主观条件）\" class=\"headerlink\" title=\"3.马克思、恩格斯的革命实践和对人类文明成果的继承与创新（主观条件）\"></a>3.马克思、恩格斯的革命实践和对人类文明成果的继承与创新（主观条件）</h5>","text":"第一章 马克思主义是关于无产阶级和人类解放的科学第一节 马克思主义的创立与发展一 马克思主义和马克思主义基本原理 概括地说，马克思主义是马克思、恩格斯创立的，为他们的后继者不断发展的科学理论体系，马克思主义是关于无产阶级和人类解放的科学。马克思主义哲学、马克思主义政治经济学和科学...","link":"","photos":[],"count_time":{"symbolsCount":371,"symbolsTime":"1 mins."},"categories":[],"tags":[{"name":"408考研","slug":"408考研","count":1,"path":"api/tags/408考研.json"}],"toc":"<ol class=\"toc\"><li class=\"toc-item toc-level-1\"><a class=\"toc-link\" href=\"#%E7%AC%AC%E4%B8%80%E7%AB%A0-%E9%A9%AC%E5%85%8B%E6%80%9D%E4%B8%BB%E4%B9%89%E6%98%AF%E5%85%B3%E4%BA%8E%E6%97%A0%E4%BA%A7%E9%98%B6%E7%BA%A7%E5%92%8C%E4%BA%BA%E7%B1%BB%E8%A7%A3%E6%94%BE%E7%9A%84%E7%A7%91%E5%AD%A6\"><span class=\"toc-text\">第一章 马克思主义是关于无产阶级和人类解放的科学</span></a><ol class=\"toc-child\"><li class=\"toc-item toc-level-2\"><a class=\"toc-link\" href=\"#%E7%AC%AC%E4%B8%80%E8%8A%82-%E9%A9%AC%E5%85%8B%E6%80%9D%E4%B8%BB%E4%B9%89%E7%9A%84%E5%88%9B%E7%AB%8B%E4%B8%8E%E5%8F%91%E5%B1%95\"><span class=\"toc-text\">第一节 马克思主义的创立与发展</span></a><ol class=\"toc-child\"><li class=\"toc-item toc-level-3\"><a class=\"toc-link\" href=\"#%E4%B8%80-%E9%A9%AC%E5%85%8B%E6%80%9D%E4%B8%BB%E4%B9%89%E5%92%8C%E9%A9%AC%E5%85%8B%E6%80%9D%E4%B8%BB%E4%B9%89%E5%9F%BA%E6%9C%AC%E5%8E%9F%E7%90%86\"><span class=\"toc-text\">一 马克思主义和马克思主义基本原理</span></a></li><li class=\"toc-item toc-level-3\"><a class=\"toc-link\" href=\"#%E4%BA%8C-%E9%A9%AC%E5%85%8B%E6%80%9D%E4%B8%BB%E4%B9%89%E7%9A%84%E5%88%9B%E7%AB%8B\"><span class=\"toc-text\">二 马克思主义的创立</span></a><ol class=\"toc-child\"><li class=\"toc-item toc-level-4\"><a class=\"toc-link\" href=\"#%EF%BC%88%E4%B8%80%EF%BC%89-%E9%A9%AC%E5%85%8B%E6%80%9D%E4%B8%BB%E4%B9%89%E4%BA%A7%E7%94%9F%E7%9A%84%E7%A4%BE%E4%BC%9A%E6%A0%B9%E6%BA%90%E3%80%81%E9%98%B6%E7%BA%A7%E5%9F%BA%E7%A1%80%E5%92%8C%E6%80%9D%E6%83%B3%E6%B8%8A%E6%BA%90\"><span class=\"toc-text\">（一） 马克思主义产生的社会根源、阶级基础和思想渊源</span></a><ol class=\"toc-child\"><li class=\"toc-item toc-level-5\"><a class=\"toc-link\" href=\"#1-%E8%B5%84%E6%9C%AC%E4%B8%BB%E4%B9%89%E7%BB%8F%E6%B5%8E%E7%9A%84%E5%8F%91%E5%B1%95%E4%B8%BA%E9%A9%AC%E5%85%8B%E6%80%9D%E4%B8%BB%E4%B9%89%E7%9A%84%E4%BA%A7%E7%94%9F%E6%8F%90%E4%BE%9B%E4%BA%86%E7%BB%8F%E6%B5%8E%E3%80%81%E7%A4%BE%E4%BC%9A%E3%80%81%E5%8E%86%E5%8F%B2%E6%9D%A1%E4%BB%B6\"><span class=\"toc-text\">1.资本主义经济的发展为马克思主义的产生提供了经济、社会、历史条件</span></a></li><li class=\"toc-item toc-level-5\"><a class=\"toc-link\" href=\"#2-%E6%97%A0%E4%BA%A7%E9%98%B6%E7%BA%A7%E5%9C%A8%E5%8F%8D%E6%8A%97%E8%B5%84%E4%BA%A7%E9%98%B6%E7%BA%A7%E7%9A%84%E6%96%97%E4%BA%89%E4%B8%AD%E9%80%90%E6%AD%A5%E8%B5%B0%E5%90%91%E8%87%AA%E8%A7%89%EF%BC%8C%E5%AF%B9%E7%A7%91%E5%AD%A6%E7%90%86%E8%AE%BA%E7%9A%84%E6%8C%87%E5%AF%BC%E6%8F%90%E5%87%BA%E4%BA%86%E5%BC%BA%E7%83%88%E7%9A%84%E9%9C%80%E6%B1%82%EF%BC%88%E9%A9%AC%E5%85%8B%E6%80%9D%E4%B8%BB%E4%B9%89%E4%BA%A7%E7%94%9F%E7%9A%84%E9%98%B6%E7%BA%A7%E5%9F%BA%E7%A1%80%E5%92%8C%E5%AE%9E%E8%B7%B5%E5%9F%BA%E7%A1%80%EF%BC%89\"><span class=\"toc-text\">2.无产阶级在反抗资产阶级的斗争中逐步走向自觉，对科学理论的指导提出了强烈的需求（马克思主义产生的阶级基础和实践基础）</span></a></li><li class=\"toc-item toc-level-5\"><a class=\"toc-link\" href=\"#3-%E9%A9%AC%E5%85%8B%E6%80%9D%E3%80%81%E6%81%A9%E6%A0%BC%E6%96%AF%E7%9A%84%E9%9D%A9%E5%91%BD%E5%AE%9E%E8%B7%B5%E5%92%8C%E5%AF%B9%E4%BA%BA%E7%B1%BB%E6%96%87%E6%98%8E%E6%88%90%E6%9E%9C%E7%9A%84%E7%BB%A7%E6%89%BF%E4%B8%8E%E5%88%9B%E6%96%B0%EF%BC%88%E4%B8%BB%E8%A7%82%E6%9D%A1%E4%BB%B6%EF%BC%89\"><span class=\"toc-text\">3.马克思、恩格斯的革命实践和对人类文明成果的继承与创新（主观条件）</span></a></li></ol></li></ol></li></ol></li></ol></li></ol>","author":{"name":"Liu Wei","slug":"blog-author","avatar":"https://img-blog.csdnimg.cn/20210313122054101.png","link":"/","description":"","socials":{"github":"","twitter":"","stackoverflow":"","wechat":"","qq":"","weibo":"","zhihu":"","csdn":"","juejin":"","customs":{}}},"mapped":true,"prev_post":{},"next_post":{}}